splash/__init__.py
splash/admin.py
splash/middleware.py
splash/models.py
splash/migrations/0001_initial.py
splash/migrations/__init__.py
django_splash-1.3.0.dist-info/AUTHORS
django_splash-1.3.0.dist-info/LICENSE.txt
django_splash-1.3.0.dist-info/METADATA
django_splash-1.3.0.dist-info/WHEEL
django_splash-1.3.0.dist-info/top_level.txt
django_splash-1.3.0.dist-info/RECORD
