Metadata-Version: 2.1
Name: django-splash
Version: 1.3.0
Summary: Splash screen middleware for Django apps
Home-page: https://github.com/openedx/django-splash
Author: edX
Author-email: oscm@edx.org
License: Apache Software License 2.0
Keywords: Django edx
Classifier: Development Status :: 3 - Alpha
Classifier: Framework :: Django
Classifier: Framework :: Django :: 3.2
Classifier: Framework :: Django :: 4.0
Classifier: Framework :: Django :: 4.2
Classifier: Intended Audience :: Developers
Classifier: License :: OSI Approved :: Apache Software License
Classifier: Natural Language :: English
Classifier: Programming Language :: Python :: 3
Classifier: Programming Language :: Python :: 3.8
License-File: LICENSE.txt
License-File: AUTHORS
Requires-Dist: Django (<5.0)
